base/__init__.py
base/api_client.py
base/api_response.py
base/configuration.py
base/exceptions.py
base/py.typed
base/rest.py
base/api/__init__.py
base/api/default_api.py
base/models/__init__.py
base/models/completion_api.py
base/models/completion_creation_forbidden_error.py
base/models/completion_request.py
base/models/completion_usage.py
base/models/conflicting_name_forbidden_error.py
base/models/error.py
base/models/json_schema_api.py
base/models/json_schema_creation_forbidden_error.py
base/models/json_schema_creation_forbidden_error_detail.py
base/models/json_schema_filter.py
base/models/json_schema_status.py
base/models/json_schema_status_pagination_output.py
base/models/not_found_error.py
base/models/not_implemented_error.py
base/models/pagination_input.py
base/models/path_js_id.py
base/models/response.py
base/models/status.py
base/models/streaming_not_implemented_error.py
base/models/success.py
base/models/too_many_requests_error.py
base/models/unauthorized_error.py
base/models/validation_error.py
dottxt/__init__.py
dottxt/_version.py
dottxt/cli.py
dottxt/client.py
dottxt/config.py
dottxt-0.1.4.dist-info/METADATA
dottxt-0.1.4.dist-info/WHEEL
dottxt-0.1.4.dist-info/entry_points.txt
dottxt-0.1.4.dist-info/top_level.txt
dottxt-0.1.4.dist-info/RECORD
