Metadata-Version: 2.1
Name: dottxt
Version: 0.1.4
Summary: .txt Python SDK
Author: .txt Developers
Project-URL: repository, https://github.com/dottxt-ai/dottxt-python
Requires-Dist: pydantic-settings>=2
Requires-Dist: pydantic>=2
Requires-Dist: python_dateutil>=2.8.2
Requires-Dist: typing-extensions>=4.7.1
Requires-Dist: urllib3<3.0.0,>=1.25.3
Requires-Dist: backoff>=2.2.1
Requires-Dist: click>=7.0
Provides-Extra: test
Requires-Dist: pytest; extra == "test"
Requires-Dist: pytest-cov; extra == "test"
